
{"ok":true,"data":{"id":"5a3c9bb6d734a23afbd096d9","name":"瑜伽·生理期轻度舒缓","description":"这是专为女性特殊的生理期设计的深度舒缓类课程，没有瑜伽基础的人群也可放心练习，只需根据自己身体能承受的强度来保持即可。在此课程中，将通过放松拉伸下半身来缓解经期不适和紧张感，并通过呼吸来平复情绪。在舒缓的体式中增强血液循环，使身体在经期依然保持活力。","detail":"<!DOCTYPE html><html><body><p>这是专为女性特殊的生理期设计的深度舒缓类课程，没有瑜伽基础的人群也可放心练习，只需根据自己身体能承受的强度来保持即可。在此课程中，将通过放松拉伸下半身来缓解经期不适和紧张感，并通过呼吸来平复情绪。在舒缓的体式中增强血液循环，使身体在经期依然保持活力。</p><h4>练习频次</h4><ul><li>推荐早起／睡前练习，根据身体情况量力而行。</li></ul><h4>注意事项</h4><ul><li>练习前2小时不要进食，保持空腹，练习效果更佳；</li><li>推荐穿着宽松有弹性的衣服，不需要穿袜子；</li><li>练习时如果感到关节疼痛或不舒服，请立即停止或调整为退阶体式；</li><li>永远不要强迫自己的身体去加深体式，而是循序渐进让体式来适应身体。</li></ul><h4>适用人群</h4><ul><li>适合各年龄层次的瑜伽爱好者，特别适合久坐的办公室人群，睡眠质量不好、早起身体僵硬者。但如果有严重的关节炎症、脊椎问题或在孕期的人群，请咨询医生后进行练习。经期请根据自己的身体状况酌情练习，尽量在经期后期练习，如有不适，立即停止。</li></ul></body></html>","picture":"http://static1.keepcdns.com/2017/12/22/18/1513939280716_4240x2384.JPG","backgroundPic":null,"duration":15,"difficulty":1,"calorie":32,"stateValue":20,"trainingType":"yoga","courseVideo":{"mode":"normal","gender":"f","url":"http://static1.keepcdns.com/yoga/video/zh/3bf1778e59ff940340da3300a15014e6.mp4","hash":"00668ba70d2160dde7d045a9dae1676b","size":18624628,"count":0},"courseAudio":null,"sections":[{"name":"Yoga Section","steps":[{"id":"5a3c9bb6d734a23afbd096ca","duration":95.8,"seekPosition":0,"exercise":{"id":"5a37706c1e82742065418f45","name":"山式站立","majorTrainingPoints":["54826e417fb786000069ad81"],"minorTrainingPoints":[],"equipment":{"name":"No equipment","units":[],"_id":"54826e417fb786000069ad59"},"description":"<!DOCTYPE html><html><body><p>null</p></body></html>","audio":null,"audioCrc32":null,"defaultHash":null,"stateValue":20,"version":47,"videos":[{"name":null,"url":"http://static1.gotokeep.com/exercises/online/20171218/20171215shengliqi_1_Normal.mp4","videolength":2959786,"videotime":1.1,"videosize":2959786,"gender":"f","thumbnail":"https://static1.gotokeep.com/picture/frame/1513917070210.jpg","status":0,"crc32":null,"count":1,"defaultHash":"c98fe7bfc281540fda4bad050736343c","mode":"normal","updated_at":null,"created_at":null}],"covers":[{"gender":"f","url":"http://static1.keepcdns.com/2017/12/22/13/1513921753336_1080x1080.jpg","coordinates":[{"x":0.49,"y":0.27,"tip":"肩部打开"},{"x":0.52,"y":0.58,"tip":"十指张开有力延伸"},{"x":0.55,"y":0.41,"tip":"收紧臀腹"}]}],"audios":null,"difficulty":1,"exerciseType":"training","_id":"5a37706c1e82742065418f45"}},{"id":"5a3c9bb6d734a23afbd096cb","duration":55.9,"seekPosition":95800,"exercise":{"id":"5a37706c1e82742065418f46","name":"右侧站立脊柱扭转","majorTrainingPoints":["54826e417fb786000069ad81"],"minorTrainingPoints":[],"equipment":{"name":"No equipment","units":[],"_id":"54826e417fb786000069ad59"},"description":"<!DOCTYPE html><html><body><p>null</p></body></html>","audio":null,"audioCrc32":null,"defaultHash":null,"stateValue":20,"version":47,"videos":[{"name":null,"url":"http://static1.gotokeep.com/exercises/online/20171218/20171215shengliqi_2_Normal.mp4","videolength":1633581,"videotime":1.1,"videosize":1633581,"gender":"f","thumbnail":"https://static1.gotokeep.com/picture/frame/1513917079286.jpg","status":0,"crc32":null,"count":1,"defaultHash":"a56403999b021c10634781c2483775b2","mode":"normal","updated_at":null,"created_at":null}],"covers":[{"gender":"f","url":"http://static1.keepcdns.com/2017/12/22/13/1513921761651_1080x1080.jpg","coordinates":[{"x":0.45,"y":0.23,"tip":"右肩向后打开"},{"x":0.47,"y":0.49,"tip":"Tighten your glutes"}]}],"audios":null,"difficulty":1,"exerciseType":"training","_id":"5a37706c1e82742065418f46"}},{"id":"5a3c9bb6d734a23afbd096cc","duration":56.3,"seekPosition":151700,"exercise":{"id":"5a37706c1e82742065418f47","name":"左侧站立脊柱扭转","majorTrainingPoints":["54826e417fb786000069ad81"],"minorTrainingPoints":[],"equipment":{"name":"No equipment","units":[],"_id":"54826e417fb786000069ad59"},"description":"<!DOCTYPE html><html><body><p>null</p></body></html>","audio":null,"audioCrc32":null,"defaultHash":null,"stateValue":20,"version":47,"videos":[{"name":null,"url":"http://static1.gotokeep.com/exercises/online/20171218/20171215shengliqi_3_Normal.mp4","videolength":1579328,"videotime":1.1,"videosize":1579328,"gender":"f","thumbnail":"https://static1.gotokeep.com/picture/frame/1513917085579.jpg","status":0,"crc32":null,"count":1,"defaultHash":"7c0582416b332fe0c028e3e66506657a","mode":"normal","updated_at":null,"created_at":null}],"covers":[{"gender":"f","url":"http://static1.keepcdns.com/2017/12/22/13/1513921770435_1080x1080.jpg","coordinates":[{"x":0.43,"y":0.25,"tip":"左肩向后打开"},{"x":0.49,"y":0.47,"tip":"Tighten your glutes"}]}],"audios":null,"difficulty":1,"exerciseType":"training","_id":"5a37706c1e82742065418f47"}},{"id":"5a3c9bb6d734a23afbd096cd","duration":48.1,"seekPosition":208000,"exercise":{"id":"5a37706c1e82742065418f48","name":"右侧单手树式","majorTrainingPoints":["54826e417fb786000069ad81"],"minorTrainingPoints":[],"equipment":{"name":"No equipment","units":[],"_id":"54826e417fb786000069ad59"},"description":"<!DOCTYPE html><html><body><p>null</p></body></html>","audio":null,"audioCrc32":null,"defaultHash":null,"stateValue":20,"version":47,"videos":[{"name":null,"url":"http://static1.gotokeep.com/exercises/online/20171218/20171215shengliqi_4_Normal.mp4","videolength":1413529,"videotime":1.1,"videosize":1413529,"gender":"f","thumbnail":"https://static1.gotokeep.com/picture/frame/1513917094321.jpg","status":0,"crc32":null,"count":1,"defaultHash":"45bf0e64f9f22f939d9d2d089a44a4a7","mode":"normal","updated_at":null,"created_at":null}],"covers":[{"gender":"f","url":"http://static1.keepcdns.com/2017/12/22/13/1513921787306_1080x1080.jpg","coordinates":[{"x":0.61,"y":0.49,"tip":"髋部向左推"}]}],"audios":null,"difficulty":1,"exerciseType":"training","_id":"5a37706c1e82742065418f48"}},{"id":"5a3c9bb6d734a23afbd096ce","duration":47.0,"seekPosition":256100,"exercise":{"id":"5a37706c1e82742065418f49","name":"左侧单手树式","majorTrainingPoints":["54826e417fb786000069ad81"],"minorTrainingPoints":[],"equipment":{"name":"No equipment","units":[],"_id":"54826e417fb786000069ad59"},"description":"<!DOCTYPE html><html><body><p>null</p></body></html>","audio":null,"audioCrc32":null,"defaultHash":null,"stateValue":20,"version":47,"videos":[{"name":null,"url":"http://static1.gotokeep.com/exercises/online/20171218/20171215shengliqi_5_Normal.mp4","videolength":1318485,"videotime":1.1,"videosize":1318485,"gender":"f","thumbnail":"https://static1.gotokeep.com/picture/frame/1513917104905.jpg","status":0,"crc32":null,"count":1,"defaultHash":"f7b472737c28f7ba1de1f7af15d1e325","mode":"normal","updated_at":null,"created_at":null}],"covers":[{"gender":"f","url":"http://static1.keepcdns.com/2017/12/22/13/1513921794496_1080x1080.jpg","coordinates":[{"x":0.41,"y":0.46,"tip":"髋部向右推"}]}],"audios":null,"difficulty":1,"exerciseType":"training","_id":"5a37706c1e82742065418f49"}},{"id":"5a3c9bb6d734a23afbd096cf","duration":46.2,"seekPosition":303100,"exercise":{"id":"5a37706c1e82742065418f4a","name":"仰山式","majorTrainingPoints":["54826e417fb786000069ad81"],"minorTrainingPoints":[],"equipment":{"name":"No equipment","units":[],"_id":"54826e417fb786000069ad59"},"description":"<!DOCTYPE html><html><body><p>null</p></body></html>","audio":null,"audioCrc32":null,"defaultHash":null,"stateValue":20,"version":47,"videos":[{"name":null,"url":"http://static1.gotokeep.com/exercises/online/20171218/20171215shengliqi_6_Normal.mp4","videolength":1264956,"videotime":1.1,"videosize":1264956,"gender":"f","thumbnail":"https://static1.gotokeep.com/picture/frame/1513917120144.jpg","status":0,"crc32":null,"count":1,"defaultHash":"21d710ba1147723bdb36cbc6fd57c895","mode":"normal","updated_at":null,"created_at":null}],"covers":[{"gender":"f","url":"http://static1.keepcdns.com/2017/12/22/13/1513921802793_1080x1080.jpg","coordinates":[{"x":0.51,"y":0.09,"tip":"双臂上举"},{"x":0.57,"y":0.47,"tip":"Tighten your abs"},{"x":0.48,"y":0.59,"tip":"Tighten your glutes"}]}],"audios":null,"difficulty":1,"exerciseType":"training","_id":"5a37706c1e82742065418f4a"}},{"id":"5a3c9bb6d734a23afbd096d0","duration":32.7,"seekPosition":349300,"exercise":{"id":"5a37706c1e82742065418f4b","name":"悬挂式","majorTrainingPoints":["54826e417fb786000069ad81"],"minorTrainingPoints":[],"equipment":{"name":"No equipment","units":[],"_id":"54826e417fb786000069ad59"},"description":"<!DOCTYPE html><html><body><p>null</p></body></html>","audio":null,"audioCrc32":null,"defaultHash":null,"stateValue":20,"version":47,"videos":[{"name":null,"url":"http://static1.gotokeep.com/exercises/online/20171218/20171215shengliqi_7_Normal.mp4","videolength":989760,"videotime":1.1,"videosize":989760,"gender":"f","thumbnail":"https://static1.gotokeep.com/picture/frame/1513917131692.jpg","status":0,"crc32":null,"count":1,"defaultHash":"45791e6054e0457afddcaa6b207e7e15","mode":"normal","updated_at":null,"created_at":null}],"covers":[{"gender":"f","url":"http://static1.keepcdns.com/2017/12/22/13/1513921812348_1080x1080.jpg","coordinates":[{"x":0.65,"y":0.52,"tip":"Relax your arms"}]}],"audios":null,"difficulty":1,"exerciseType":"training","_id":"5a37706c1e82742065418f4b"}},{"id":"5a3c9bb6d734a23afbd096d1","duration":73.4,"seekPosition":382000,"exercise":{"id":"5a37706c1e82742065418f4c","name":"左侧单腿坐角式","majorTrainingPoints":["54826e417fb786000069ad81"],"minorTrainingPoints":[],"equipment":{"name":"No equipment","units":[],"_id":"54826e417fb786000069ad59"},"description":"<!DOCTYPE html><html><body><p>null</p></body></html>","audio":null,"audioCrc32":null,"defaultHash":null,"stateValue":20,"version":47,"videos":[{"name":null,"url":"http://static1.gotokeep.com/exercises/online/20171218/20171215shengliqi_8_Normal.mp4","videolength":2211757,"videotime":1.1,"videosize":2211757,"gender":"f","thumbnail":"https://static1.gotokeep.com/picture/frame/1513917141217.jpg","status":0,"crc32":null,"count":1,"defaultHash":"68a8403ef5686b900806dcf72deb0518","mode":"normal","updated_at":null,"created_at":null}],"covers":[{"gender":"f","url":"http://static1.keepcdns.com/2017/12/22/13/1513921821232_1080x1080.jpg","coordinates":[{"x":0.06,"y":0.76,"tip":"脚趾回勾"},{"x":0.59,"y":0.5,"tip":"展开双肩"}]}],"audios":null,"difficulty":1,"exerciseType":"training","_id":"5a37706c1e82742065418f4c"}},{"id":"5a3c9bb6d734a23afbd096d2","duration":37.6,"seekPosition":455400,"exercise":{"id":"5a37706c1e82742065418f4d","name":"右侧单腿坐角式","majorTrainingPoints":["54826e417fb786000069ad81"],"minorTrainingPoints":[],"equipment":{"name":"No equipment","units":[],"_id":"54826e417fb786000069ad59"},"description":"<!DOCTYPE html><html><body><p>null</p></body></html>","audio":null,"audioCrc32":null,"defaultHash":null,"stateValue":20,"version":47,"videos":[{"name":null,"url":"http://static1.gotokeep.com/exercises/online/20171218/20171215shengliqi_9_Normal.mp4","videolength":1092919,"videotime":1.1,"videosize":1092919,"gender":"f","thumbnail":"https://static1.gotokeep.com/picture/frame/1513917148951.jpg","status":0,"crc32":null,"count":1,"defaultHash":"d39a855afaac2c08731b07c41900ced2","mode":"normal","updated_at":null,"created_at":null}],"covers":[{"gender":"f","url":"http://static1.keepcdns.com/2017/12/22/13/1513921831429_1080x1080.jpg","coordinates":[{"x":0.94,"y":0.74,"tip":"脚趾回勾"},{"x":0.39,"y":0.49,"tip":"双肩展开"}]}],"audios":null,"difficulty":1,"exerciseType":"training","_id":"5a37706c1e82742065418f4d"}},{"id":"5a3c9bb6d734a23afbd096d3","duration":48.9,"seekPosition":493000,"exercise":{"id":"5a37706c1e82742065418f4e","name":"坐角式","majorTrainingPoints":["54826e417fb786000069ad81"],"minorTrainingPoints":[],"equipment":{"name":"No equipment","units":[],"_id":"54826e417fb786000069ad59"},"description":"<!DOCTYPE html><html><body><p>null</p></body></html>","audio":null,"audioCrc32":null,"defaultHash":null,"stateValue":20,"version":47,"videos":[{"name":null,"url":"http://static1.gotokeep.com/exercises/online/20171218/20171215shengliqi_10_Normal.mp4","videolength":1464222,"videotime":1.1,"videosize":1464222,"gender":"f","thumbnail":"https://static1.gotokeep.com/picture/frame/1513917161016.jpg","status":0,"crc32":null,"count":1,"defaultHash":"68ab5630740369d853b41f9802f6aa25","mode":"normal","updated_at":null,"created_at":null}],"covers":[{"gender":"f","url":"http://static1.keepcdns.com/2017/12/22/13/1513921842862_1080x1080.jpg","coordinates":[{"x":0.06,"y":0.77,"tip":"脚趾回勾"},{"x":0.38,"y":0.83,"tip":"双手放于体前"}]}],"audios":null,"difficulty":1,"exerciseType":"training","_id":"5a37706c1e82742065418f4e"}},{"id":"5a3c9bb6d734a23afbd096d4","duration":93.0,"seekPosition":541900,"exercise":{"id":"5a37706c1e82742065418f4f","name":"左侧牛面式","majorTrainingPoints":["54826e417fb786000069ad81"],"minorTrainingPoints":[],"equipment":{"name":"No equipment","units":[],"_id":"54826e417fb786000069ad59"},"description":"<!DOCTYPE html><html><body><p>null</p></body></html>","audio":null,"audioCrc32":null,"defaultHash":null,"stateValue":20,"version":47,"videos":[{"name":null,"url":"http://static1.gotokeep.com/exercises/online/20171218/20171215shengliqi_11_Normal.mp4","videolength":2776610,"videotime":1.1,"videosize":2776610,"gender":"f","thumbnail":"https://static1.gotokeep.com/picture/frame/1513921652522.jpg","status":0,"crc32":null,"count":1,"defaultHash":"5fe7effec4eafe08c3305fb423f535ad","mode":"normal","updated_at":null,"created_at":null}],"covers":[{"gender":"f","url":"http://static1.keepcdns.com/2017/12/22/13/1513921859138_1080x1080.jpg","coordinates":[{"x":0.33,"y":0.53,"tip":"Keep your back straight"},{"x":0.43,"y":0.61,"tip":"Tighten your abs"}]}],"audios":null,"difficulty":1,"exerciseType":"training","_id":"5a37706c1e82742065418f4f"}},{"id":"5a3c9bb6d734a23afbd096d5","duration":62.8,"seekPosition":634900,"exercise":{"id":"5a37706c1e82742065418f50","name":"右侧牛面式","majorTrainingPoints":["54826e417fb786000069ad81"],"minorTrainingPoints":[],"equipment":{"name":"No equipment","units":[],"_id":"54826e417fb786000069ad59"},"description":"<!DOCTYPE html><html><body><p>null</p></body></html>","audio":null,"audioCrc32":null,"defaultHash":null,"stateValue":20,"version":47,"videos":[{"name":null,"url":"http://static1.gotokeep.com/exercises/online/20171218/20171215shengliqi_12_Normal.mp4","videolength":1874298,"videotime":1.1,"videosize":1874298,"gender":"f","thumbnail":"https://static1.gotokeep.com/picture/frame/1513917174817.jpg","status":0,"crc32":null,"count":1,"defaultHash":"3fd3482c05d8870581ab45f359511a21","mode":"normal","updated_at":null,"created_at":null}],"covers":[{"gender":"f","url":"http://static1.keepcdns.com/2017/12/22/13/1513921870793_1080x1080.jpg","coordinates":[{"x":0.37,"y":0.55,"tip":"Keep your back straight"},{"x":0.43,"y":0.61,"tip":"Tighten your abs"}]}],"audios":null,"difficulty":1,"exerciseType":"training","_id":"5a37706c1e82742065418f50"}},{"id":"5a3c9bb6d734a23afbd096d6","duration":122.0,"seekPosition":697699,"exercise":{"id":"5a37706c1e82742065418f51","name":"猫伸展式","majorTrainingPoints":["54826e417fb786000069ad81"],"minorTrainingPoints":[],"equipment":{"name":"No equipment","units":[],"_id":"54826e417fb786000069ad59"},"description":"<!DOCTYPE html><html><body><p>null</p></body></html>","audio":null,"audioCrc32":null,"defaultHash":null,"stateValue":20,"version":47,"videos":[{"name":null,"url":"http://static1.gotokeep.com/exercises/online/20171218/20171215shengliqi_13_Normal.mp4","videolength":3531337,"videotime":1.1,"videosize":3531337,"gender":"f","thumbnail":"https://static1.gotokeep.com/picture/frame/1513917182875.jpg","status":0,"crc32":null,"count":1,"defaultHash":"4ed2bc5cfd9fbed34522d3ecf94ebb10","mode":"normal","updated_at":null,"created_at":null}],"covers":[{"gender":"f","url":"http://static1.keepcdns.com/2017/12/22/13/1513921884497_1080x1080.jpg","coordinates":[{"x":0.39,"y":0.51,"tip":"臀部上提"},{"x":0.18,"y":0.75,"tip":"脚趾回勾"}]},{"gender":"f","url":"http://static1.keepcdns.com/2017/12/22/13/1513921894318_1080x1080.jpg","coordinates":[{"x":0.48,"y":0.44,"tip":"腹部用力向上推"}]}],"audios":null,"difficulty":1,"exerciseType":"training","_id":"5a37706c1e82742065418f51"}},{"id":"5a3c9bb6d734a23afbd096d7","duration":54.1,"seekPosition":819699,"exercise":{"id":"5a37706c1e82742065418f52","name":"大拜式","majorTrainingPoints":["54826e417fb786000069ad81"],"minorTrainingPoints":[],"equipment":{"name":"No equipment","units":[],"_id":"54826e417fb786000069ad59"},"description":"<!DOCTYPE html><html><body><p>null</p></body></html>","audio":null,"audioCrc32":null,"defaultHash":null,"stateValue":20,"version":47,"videos":[{"name":null,"url":"http://static1.gotokeep.com/exercises/online/20171218/20171215shengliqi_14_Normal.mp4","videolength":1547619,"videotime":1.1,"videosize":1547619,"gender":"f","thumbnail":"https://static1.gotokeep.com/picture/frame/1513917190207.jpg","status":0,"crc32":null,"count":1,"defaultHash":"2146350e8d831dd742e41bddc523e8b1","mode":"normal","updated_at":null,"created_at":null}],"covers":[{"gender":"f","url":"http://static1.keepcdns.com/2017/12/22/13/1513921908645_1080x1080.jpg","coordinates":[{"x":0.78,"y":0.69,"tip":"前额点地"},{"x":0.24,"y":0.64,"tip":"臀部落于脚后跟上"}]}],"audios":null,"difficulty":1,"exerciseType":"training","_id":"5a37706c1e82742065418f52"}},{"id":"5a3c9bb6d734a23afbd096d8","duration":42.3,"seekPosition":873800,"exercise":{"id":"5a37706c1e82742065418f53","name":"祈祷式结束","majorTrainingPoints":["54826e417fb786000069ad81"],"minorTrainingPoints":[],"equipment":{"name":"No equipment","units":[],"_id":"54826e417fb786000069ad59"},"description":"<!DOCTYPE html><html><body><p>null</p></body></html>","audio":null,"audioCrc32":null,"defaultHash":null,"stateValue":20,"version":47,"videos":[{"name":null,"url":"http://static1.gotokeep.com/exercises/online/20171218/20171215shengliqi_15_Normal.mp4","videolength":1291872,"videotime":1.1,"videosize":1291872,"gender":"f","thumbnail":"https://static1.gotokeep.com/picture/frame/1513917198697.jpg","status":0,"crc32":null,"count":1,"defaultHash":"119ba68bfcd98c77e292dbf146c7ea12","mode":"normal","updated_at":null,"created_at":null}],"covers":[{"gender":"f","url":"http://static1.keepcdns.com/2017/12/22/13/1513921917645_1080x1080.jpg","coordinates":[{"x":0.45,"y":0.42,"tip":"双手于胸前合十"}]}],"audios":null,"difficulty":1,"exerciseType":"training","_id":"5a37706c1e82742065418f53"}}]}]},"errorCode":0,"text":""}